pyacoustics/__init__.py
pyacoustics/aggregate_features.py
pyacoustics/intensity_and_pitch/__init__.py
pyacoustics/intensity_and_pitch/get_f0.py
pyacoustics/signals/__init__.py
pyacoustics/signals/audio_scripts.py
pyacoustics/signals/data_fitting.py
pyacoustics/signals/filters.py
pyacoustics/speech_detection/__init__.py
pyacoustics/speech_detection/common.py
pyacoustics/speech_detection/naive_vad.py
pyacoustics/speech_detection/naive_vad_efficient.py
pyacoustics/speech_detection/segment_stereo_speech.py
pyacoustics/speech_detection/segment_stereo_speech_efficient.py
pyacoustics/speech_detection/split_on_tone.py
pyacoustics/speech_detection/textgrids.py
pyacoustics/speech_rate/__init__.py
pyacoustics/speech_rate/dictionary_estimate.py
pyacoustics/speech_rate/uwe_sr.py
pyacoustics/text/__init__.py
pyacoustics/text/frequency.py
pyacoustics/text/transcript.py
pyacoustics/textgrids/__init__.py
pyacoustics/textgrids/syllabify_textgrids.py
pyacoustics/textgrids/textgrids.py
pyacoustics/utilities/__init__.py
pyacoustics/utilities/error_utils.py
pyacoustics/utilities/filters.py
pyacoustics/utilities/matlab.py
pyacoustics/utilities/my_math.py
pyacoustics/utilities/normalize.py
pyacoustics/utilities/sequences.py
pyacoustics/utilities/statistics.py
pyacoustics/utilities/utils.py
pyacoustics-2.0.0.dist-info/LICENSE
pyacoustics-2.0.0.dist-info/METADATA
pyacoustics-2.0.0.dist-info/WHEEL
pyacoustics-2.0.0.dist-info/top_level.txt
pyacoustics-2.0.0.dist-info/RECORD
