Metadata-Version: 2.1
Name: pyacoustics
Version: 2.0.0
Summary: A collection of python scripts for extracting and analyzing acoustics from audio files.
Home-page: https://github.com/timmahrt/pyAcoustics
Author: Tim Mahrt
Author-email: timmahrt@gmail.com
License: LICENSE
Platform: UNKNOWN
Requires-Python: >3.6.0
License-File: LICENSE
Requires-Dist: praatio (~=6.0)
Requires-Dist: typing-extensions
